couchbase_infrastructure/__init__.py
couchbase_infrastructure/cli.py
couchbase_infrastructure/client.py
couchbase_infrastructure/config.py
couchbase_infrastructure/resources.py
couchbase_infrastructure-0.1.21.dist-info/licenses/LICENSE
couchbase_infrastructure-0.1.21.dist-info/METADATA
couchbase_infrastructure-0.1.21.dist-info/WHEEL
couchbase_infrastructure-0.1.21.dist-info/entry_points.txt
couchbase_infrastructure-0.1.21.dist-info/top_level.txt
couchbase_infrastructure-0.1.21.dist-info/RECORD
