Metadata-Version: 2.4
Name: couchbase-infrastructure
Version: 0.1.21
Summary: CLI tool and Python library for automating Couchbase Capella infrastructure setup
Author-email: Couchbase <support@couchbase.com>
License: Apache-2.0
Project-URL: Homepage, https://github.com/couchbase/couchbase-infrastructure
Project-URL: Documentation, https://github.com/couchbase/couchbase-infrastructure#readme
Project-URL: Repository, https://github.com/couchbase/couchbase-infrastructure
Project-URL: Bug Tracker, https://github.com/couchbase/couchbase-infrastructure/issues
Keywords: couchbase,capella,infrastructure,automation,cli
Classifier: Development Status :: 3 - Alpha
Classifier: Intended Audience :: Developers
Classifier: License :: OSI Approved :: Apache Software License
Classifier: Programming Language :: Python :: 3
Classifier: Programming Language :: Python :: 3.9
Classifier: Programming Language :: Python :: 3.10
Classifier: Programming Language :: Python :: 3.11
Classifier: Programming Language :: Python :: 3.12
Classifier: Topic :: Software Development :: Libraries :: Python Modules
Classifier: Topic :: Database
Requires-Python: >=3.9
License-File: LICENSE
Requires-Dist: httpx>=0.27.0
Requires-Dist: python-dotenv>=1.0.0
Requires-Dist: click>=8.1.0
Requires-Dist: rich>=13.0.0
Provides-Extra: dev
Requires-Dist: pytest>=8.0.0; extra == "dev"
Requires-Dist: pytest-cov>=4.1.0; extra == "dev"
Requires-Dist: ruff>=0.5.0; extra == "dev"
Requires-Dist: black>=24.0.0; extra == "dev"
Requires-Dist: mypy>=1.10.0; extra == "dev"
Dynamic: license-file
